squirtle/__init__.py
squirtle/converters.py
squirtle/errors.py
squirtle/type_mappings.py
squirtle-0.2.0.dist-info/licenses/LICENSE
squirtle-0.2.0.dist-info/METADATA
squirtle-0.2.0.dist-info/WHEEL
squirtle-0.2.0.dist-info/top_level.txt
squirtle-0.2.0.dist-info/RECORD
