Metadata-Version: 2.4
Name: squirtle
Version: 0.2.0
Summary: Convert between Polars schemas and SQLAlchemy/SQLModel classes with ease
Author-email: Odos Matthews <odosmatthews@gmail.com>
License: MIT
Project-URL: Homepage, https://github.com/eddiethedean/squirtle
Project-URL: Repository, https://github.com/eddiethedean/squirtle
Project-URL: Issues, https://github.com/eddiethedean/squirtle/issues
Keywords: polars,sqlalchemy,sqlmodel,schema,conversion,orm
Classifier: Development Status :: 3 - Alpha
Classifier: Intended Audience :: Developers
Classifier: License :: OSI Approved :: MIT License
Classifier: Programming Language :: Python :: 3
Classifier: Programming Language :: Python :: 3.8
Classifier: Programming Language :: Python :: 3.9
Classifier: Programming Language :: Python :: 3.10
Classifier: Programming Language :: Python :: 3.11
Classifier: Programming Language :: Python :: 3.12
Classifier: Topic :: Software Development :: Libraries :: Python Modules
Classifier: Topic :: Database
Requires-Python: >=3.8
License-File: LICENSE
Requires-Dist: polars>=0.19.0
Requires-Dist: sqlalchemy>=1.4.0
Provides-Extra: sqlmodel
Requires-Dist: sqlmodel>=0.0.8; extra == "sqlmodel"
Provides-Extra: dev
Requires-Dist: pytest>=7.0.0; extra == "dev"
Requires-Dist: pytest-cov>=4.0.0; extra == "dev"
Requires-Dist: black>=23.0.0; extra == "dev"
Requires-Dist: ruff>=0.1.0; extra == "dev"
Requires-Dist: mypy<1.8; extra == "dev"
Dynamic: license-file
